fold_models/__init__.py
fold_models/ar.py
fold_models/arima.py
fold_models/baseline.py
fold_models-0.1.2.dist-info/METADATA
fold_models-0.1.2.dist-info/WHEEL
fold_models-0.1.2.dist-info/licenses/LICENSE
fold_models-0.1.2.dist-info/RECORD
