Metadata-Version: 2.1
Name: fold-models
Version: 0.1.2
Summary: Models for fold.
Project-URL: Documentation, https://dream-faster.github.io/fold-models
Project-URL: Issues, https://github.com/dream-faster/fold-models/issues
Project-URL: Source, https://github.com/dream-faster/fold-models
Author-email: Mark Aron Szulyovszky <mark@dreamfaster.ai>, Daniel Szemerey <daniel@dreamfaster.ai>
License:                             LICENSE
License-File: LICENSE
Keywords: financial-machine-learning,forecast,forecasting,machine-learning,models,nowcast,time-series,time-series-classification,time-series-regression
Classifier: Development Status :: 5 - Production/Stable
Classifier: License :: Other/Proprietary License
Classifier: Operating System :: OS Independent
Classifier: Programming Language :: Python
Classifier: Programming Language :: Python :: 3.7
Classifier: Programming Language :: Python :: 3.8
Classifier: Programming Language :: Python :: 3.9
Classifier: Programming Language :: Python :: 3.10
Classifier: Programming Language :: Python :: Implementation :: CPython
Classifier: Programming Language :: Python :: Implementation :: PyPy
Requires-Python: >=3.7
Requires-Dist: fold-core~=0.1
Requires-Dist: numpy
Requires-Dist: scikit-learn
Provides-Extra: docs
Requires-Dist: mkdocs-autorefs; extra == 'docs'
Requires-Dist: mkdocs-include-markdown-plugin; extra == 'docs'
Requires-Dist: mkdocs-material; extra == 'docs'
Requires-Dist: mkdocstrings-python; extra == 'docs'
Provides-Extra: quality
Requires-Dist: black~=22.10.0; extra == 'quality'
Requires-Dist: flake8~=4.0.1; extra == 'quality'
Requires-Dist: isort~=5.10.1; extra == 'quality'
Requires-Dist: pre-commit~=2.20.0; extra == 'quality'
Provides-Extra: tests
Requires-Dist: fold-core~=0.1; extra == 'tests'
Requires-Dist: fold-wrappers~=0.1; extra == 'tests'
Requires-Dist: pytest~=7.1.2; extra == 'tests'
Requires-Dist: statsforecast; extra == 'tests'
Requires-Dist: statsmodels; extra == 'tests'
